datatools/__init__.py
datatools/base.py
datatools/converter.py
datatools/process.py
datatools/storage.py
datatools/utils.py
wingechr_datatools-0.14.0.dist-info/METADATA
wingechr_datatools-0.14.0.dist-info/WHEEL
wingechr_datatools-0.14.0.dist-info/top_level.txt
wingechr_datatools-0.14.0.dist-info/RECORD
