Metadata-Version: 2.4
Name: wingechr-datatools
Version: 0.14.0
Summary: TODO
Author-email: Christian Winger <c@wingechr.de>
Requires-Python: <3.14,>=3.9
Requires-Dist: appdirs>=1.4.4
Requires-Dist: chardet>=5.2.0
Requires-Dist: jsonpath-ng>=1.7.0
Requires-Dist: openpyxl>=3.1.5
Requires-Dist: pandas>=2
Requires-Dist: pyodbc>=5.2.0
Requires-Dist: rdflib>=7.1.4
Requires-Dist: requests>=2
Requires-Dist: sqlalchemy>=2.0.41
Requires-Dist: sqlparse>=0.5.3
Requires-Dist: tzlocal>=5.3.1
Requires-Dist: unidecode>=1.4.0
